Workbook

Sheet Customers
A1: Customer_ID | B1: Customer_Name | C1: Region | D1: Segment
A2: Cust 6583 | B2: Aman Iyer | C2: Asia | D2: Home Office
A3: Cust 2144 | B3: Riya Kapoor | C3: South America | D3: Consumer
A4: Cust 5998 | B4: Ira Nair | C4: North America | D4: Consumer
A5: Cust 7136 | B5: Anushka Pillai | C5: Africa | D5: Consumer
A6: Cust 6506 | B6: Sneha Rao | C6: Asia | D6: Home Office
A7: Cust 3909 | B7: Vivek Patel | C7: Africa | D7: Consumer
A8: Cust 7887 | B8: Nisha Yadav | C8: South America | D8: Consumer
A9: Cust 5301 | B9: Dev Ghosh | C9: Africa | D9: Consumer
A10: Cust 2284 | B10: Manav Joshi | C10: South America | D10: Corporate
A11: Cust 3732 | B11: Riya Gupta | C11: Europe | D11: Corporate
A12: Cust 1462 | B12: Arjun Reddy | C12: North America | D12: Consumer
... A501: Cust 5530 | B501: Kavya Verma | C501: Africa | D501: Corporate

Sheet Orders
A1: Order_ID | B1: Order_Date | C1: Customer_ID | D1: Product_Category | E1: Sales | F1: Quantity | G1: Profit | H1: Discount | I1: Region | J1: Segment | K1: Month
A2: REG100000 | B2: 44980 | C2: Cust 6583 | D2: Electronics | E2: 2290.4 | F2: 14 | G2: 658 | H2: 0 | I2: =VLOOKUP(C2,Table1[#All],3,FALSE) -> Asia | J2: =VLOOKUP(C2,Table1[#All],4,FALSE) -> Home Office | K2: =TEXT(Table13[[#This Row],[Order_Date]],"mmm-yyyy") -> Feb-2023
A3: REG100001 | B3: 45645 | C3: Cust 2144 | D3: Furniture | E3: 544.01 | F3: 1 | G3: 64 | H3: 0 | I3: =VLOOKUP(C3,Table1[#All],3,FALSE) -> South America | J3: =VLOOKUP(C3,Table1[#All],4,FALSE) -> Consumer | K3: =TEXT(Table13[[#This Row],[Order_Date]],"mmm-yyyy") -> Dec-2024
A4: REG100002 | B4: 45204 | C4: Cust 5998 | D4: Furniture | E4: 4361.868 | F4: 14 | G4: 146 | H4: 0.1 | I4: =VLOOKUP(C4,Table1[#All],3,FALSE) -> North America | J4: =VLOOKUP(C4,Table1[#All],4,FALSE) -> Consumer | K4: =TEXT(Table13[[#This Row],[Order_Date]],"mmm-yyyy") -> Oct-2023
A5: REG100003 | B5: 45714 | C5: Cust 7136 | D5: Electronics | E5: 5887.746 | F5: 18 | G5: 712 | H5: 0.15 | I5: =VLOOKUP(C5,Table1[#All],3,FALSE) -> Africa | J5: =VLOOKUP(C5,Table1[#All],4,FALSE) -> Consumer | K5: =TEXT(Table13[[#This Row],[Order_Date]],"mmm-yyyy") -> Feb-2025
A6: REG100004 | B6: 45101 | C6: Cust 6506 | D6: Electronics | E6: 4279.68 | F6: 18 | G6: 1151 | H6: 0 | I6: =VLOOKUP(C6,Table1[#All],3,FALSE) -> Asia | J6: =VLOOKUP(C6,Table1[#All],4,FALSE) -> Home Office | K6: =TEXT(Table13[[#This Row],[Order_Date]],"mmm-yyyy") -> Jun-2023
A7: REG100005 | B7: 45342 | C7: Cust 3909 | D7: Clothing | E7: 654.653 | F7: 2 | G7: 247 | H7: 0.15 | I7: =VLOOKUP(C7,Table1[#All],3,FALSE) -> Africa | J7: =VLOOKUP(C7,Table1[#All],4,FALSE) -> Consumer | K7: =TEXT(Table13[[#This Row],[Order_Date]],"mmm-yyyy") -> Feb-2024
A8: REG100006 | B8: 45231 | C8: Cust 7887 | D8: Clothing | E8: 110.25 | F8: 7 | G8: -275 | H8: 0.1 | I8: =VLOOKUP(C8,Table1[#All],3,FALSE) -> South America | J8: =VLOOKUP(C8,Table1[#All],4,FALSE) -> Consumer | K8: =TEXT(Table13[[#This Row],[Order_Date]],"mmm-yyyy") -> Nov-2023
A9: REG100007 | B9: 45170 | C9: Cust 5301 | D9: Clothing | E9: 842.061 | F9: 3 | G9: -213 | H9: 0.15 | I9: =VLOOKUP(C9,Table1[#All],3,FALSE) -> Africa | J9: =VLOOKUP(C9,Table1[#All],4,FALSE) -> Consumer | K9: =TEXT(Table13[[#This Row],[Order_Date]],"mmm-yyyy") -> Sep-2023
A10: REG100008 | B10: 45581 | C10: Cust 2284 | D10: Clothing | E10: 1231.314 | F10: 3 | G10: -44 | H10: 0.05 | I10: =VLOOKUP(C10,Table1[#All],3,FALSE) -> South America | J10: =VLOOKUP(C10,Table1[#All],4,FALSE) -> Corporate | K10: =TEXT(Table13[[#This Row],[Order_Date]],"mmm-yyyy") -> Oct-2024
A11: REG100009 | B11: 45780 | C11: Cust 3732 | D11: Clothing | E11: 1454.76 | F11: 5 | G11: -54 | H11: 0.1 | I11: =VLOOKUP(C11,Table1[#All],3,FALSE) -> Europe | J11: =VLOOKUP(C11,Table1[#All],4,FALSE) -> Corporate | K11: =TEXT(Table13[[#This Row],[Order_Date]],"mmm-yyyy") -> May-2025
A12: REG100010 | B12: 45569 | C12: Cust 1462 | D12: Clothing | E12: 6671.9475 | F12: 15 | G12: -190 | H12: 0.15 | I12: =VLOOKUP(C12,Table1[#All],3,FALSE) -> North America | J12: =VLOOKUP(C12,Table1[#All],4,FALSE) -> Consumer | K12: =TEXT(Table13[[#This Row],[Order_Date]],"mmm-yyyy") -> Oct-2024
A13: REG100011 | B13: 45633 | C13: Cust 4330 | D13: Electronics | E13: 3545.685 | F13: 19 | G13: -234 | H13: 0.1 | I13: =VLOOKUP(C13,Table1[#All],3,FALSE) -> Asia | J13: =VLOOKUP(C13,Table1[#All],4,FALSE) -> Corporate | K13: =TEXT(Table13[[#This Row],[Order_Date]],"mmm-yyyy") -> Dec-2024
... A501: REG100499 | B501: 45457 | C501: Cust 5530 | D501: Clothing | E501: 517.374 | F501: 2 | G501: 17 | H501: 0.1 | I501: =VLOOKUP(C501,Table1[#All],3,FALSE) -> Asia | J501: =VLOOKUP(C501,Table1[#All],4,FALSE) -> Consumer | K501: =TEXT(Table13[[#This Row],[Order_Date]],"mmm-yyyy") -> Jun-2024

Sheet Monthly Sales Performance
A1: Month | B1: Current_Month_Sales | C1: Previous_Month_Sales | D1: Sales Variance | E1: Growth%
A2: =TEXT(Table13[[#This Row],[Order_Date]],"mmm-yyyy") -> Feb-2023 | B2: =SUMIF(Orders!K:K,A2,Orders!E:E) -> 31599.204 | D2: =B2-C2 -> 31599.204 | E2: =IF(C2=0,0,(D2/C2)*100) -> 0
A3: =TEXT(Table13[[#This Row],[Order_Date]],"mmm-yyyy") -> Dec-2024 | B3: =SUMIF(Orders!K:K,A3,Orders!E:E) -> 27646.277 | C3: =B2 -> 31599.204 | D3: =B3-C3 -> -3952.9275 | E3: =IF(C3=0,0,(D3/C3)*100) -> -12.509579
A4: =TEXT(Table13[[#This Row],[Order_Date]],"mmm-yyyy") -> Oct-2023 | B4: =SUMIF(Orders!K:K,A4,Orders!E:E) -> 35673.452 | C4: =B3 -> 27646.277 | D4: =B4-C4 -> 8027.1745 | E4: =IF(C4=0,0,(D4/C4)*100) -> 29.035282
A5: =TEXT(Table13[[#This Row],[Order_Date]],"mmm-yyyy") -> Feb-2025 | B5: =SUMIF(Orders!K:K,A5,Orders!E:E) -> 43736.825 | C5: =B4 -> 35673.452 | D5: =B5-C5 -> 8063.373 | E5: =IF(C5=0,0,(D5/C5)*100) -> 22.603288
A6: =TEXT(Table13[[#This Row],[Order_Date]],"mmm-yyyy") -> Jun-2023 | B6: =SUMIF(Orders!K:K,A6,Orders!E:E) -> 62271.799 | C6: =B5 -> 43736.825 | D6: =B6-C6 -> 18534.975 | E6: =IF(C6=0,0,(D6/C6)*100) -> 42.378418
A7: =TEXT(Table13[[#This Row],[Order_Date]],"mmm-yyyy") -> Feb-2024 | B7: =SUMIF(Orders!K:K,A7,Orders!E:E) -> 63420.142 | C7: =B6 -> 62271.799 | D7: =B7-C7 -> 1148.343 | E7: =IF(C7=0,0,(D7/C7)*100) -> 1.8440819
A8: =TEXT(Table13[[#This Row],[Order_Date]],"mmm-yyyy") -> Nov-2023 | B8: =SUMIF(Orders!K:K,A8,Orders!E:E) -> 87862.096 | C8: =B7 -> 63420.142 | D8: =B8-C8 -> 24441.954 | E8: =IF(C8=0,0,(D8/C8)*100) -> 38.539733
A9: =TEXT(Table13[[#This Row],[Order_Date]],"mmm-yyyy") -> Sep-2023 | B9: =SUMIF(Orders!K:K,A9,Orders!E:E) -> 54431.52 | C9: =B8 -> 87862.096 | D9: =B9-C9 -> -33430.575 | E9: =IF(C9=0,0,(D9/C9)*100) -> -38.048916
A10: =TEXT(Table13[[#This Row],[Order_Date]],"mmm-yyyy") -> Oct-2024 | B10: =SUMIF(Orders!K:K,A10,Orders!E:E) -> 78501.204 | C10: =B9 -> 54431.52 | D10: =B10-C10 -> 24069.683 | E10: =IF(C10=0,0,(D10/C10)*100) -> 44.220119
A11: =TEXT(Table13[[#This Row],[Order_Date]],"mmm-yyyy") -> May-2025 | B11: =SUMIF(Orders!K:K,A11,Orders!E:E) -> 66561.381 | C11: =B10 -> 78501.204 | D11: =B11-C11 -> -11939.822 | E11: =IF(C11=0,0,(D11/C11)*100) -> -15.209732
A12: =TEXT(Table13[[#This Row],[Order_Date]],"mmm-yyyy") -> Oct-2024 | B12: =SUMIF(Orders!K:K,A12,Orders!E:E) -> 78501.204 | C12: =B11 -> 66561.381 | D12: =B12-C12 -> 11939.822 | E12: =IF(C12=0,0,(D12/C12)*100) -> 17.938063
A13: =TEXT(Table13[[#This Row],[Order_Date]],"mmm-yyyy") -> Dec-2024 | B13: =SUMIF(Orders!K:K,A13,Orders!E:E) -> 27646.277 | C13: =B12 -> 78501.204 | D13: =B13-C13 -> -50854.927 | E13: =IF(C13=0,0,(D13/C13)*100) -> -64.782353
A14: =TEXT(Table13[[#This Row],[Order_Date]],"mmm-yyyy") -> Jul-2023 | B14: =SUMIF(Orders!K:K,A14,Orders!E:E) -> 64908.903 | C14: =B13 -> 27646.277 | D14: =B14-C14 -> 37262.626 | E14: =IF(C14=0,0,(D14/C14)*100) -> 134.78352
... A501: =TEXT(Table13[[#This Row],[Order_Date]],"mmm-yyyy") -> Jun-2024 | B501: =SUMIF(Orders!K:K,A501,Orders!E:E) -> 28904.294 | C501: =B500 -> 46499.453 | D501: =B501-C501 -> -17595.158 | E501: =IF(C501=0,0,(D501/C501)*100) -> -37.839495

Sheet Region vs Profit Margin
A1: Region | B1: Sales | C1: Profit | D1: Profit Margin
A2: Africa | B2: =SUMIF(Orders!I:I,A2,Orders!E:E) -> 329071.06 | C2: =SUMIF(Orders!I:I,A2,Orders!G:G) -> 296 | D2: =IF(B2=0,0,C2/B2) -> 0.00089950177
A3: Asia | B3: =SUMIF(Orders!I:I,A3,Orders!E:E) -> 280117.52 | C3: =SUMIF(Orders!I:I,A3,Orders!G:G) -> 4928 | D3: =IF(B3=0,0,C3/B3) -> 0.017592616
A4: Europe | B4: =SUMIF(Orders!I:I,A4,Orders!E:E) -> 331050.63 | C4: =SUMIF(Orders!I:I,A4,Orders!G:G) -> 158 | D4: =IF(B4=0,0,C4/B4) -> 0.00047726838
A5: North America | B5: =SUMIF(Orders!I:I,A5,Orders!E:E) -> 423725.88 | C5: =SUMIF(Orders!I:I,A5,Orders!G:G) -> 5181 | D5: =IF(B5=0,0,C5/B5) -> 0.012227245
A6: South America | B6: =SUMIF(Orders!I:I,A6,Orders!E:E) -> 303377.34 | C6: =SUMIF(Orders!I:I,A6,Orders!G:G) -> 7953 | D6: =IF(B6=0,0,C6/B6) -> 0.026214878

Sheet Category vs Growth%
A1: Product_Category | B1: Current_Sales | C1: Previous_Sales | D1: Growth%
A2: Clothing | B2: =SUMIF(Orders!D:D,A2,'Monthly Sales Performance'!B:B) -> 15458995 | C2: =SUMIF(Orders!D:D,A2,Orders!E:E) -> 969148.54 | D2: =INDEX(Table3[#All],MATCH(A2,Table13[#All],0)) -> #N/A
A3: Electronics | B3: =SUMIF(Orders!D:D,A3,'Monthly Sales Performance'!B:B) -> 6906071.3 | C3: =SUMIF(Orders!D:D,A3,Orders!E:E) -> 395454.33 | D3: =INDEX(Table3[#All],MATCH(A3,Table13[#All],0)) -> #N/A
A4: Furniture | B4: =SUMIF(Orders!D:D,A4,'Monthly Sales Performance'!B:B) -> 4636999.9 | C4: =SUMIF(Orders!D:D,A4,Orders!E:E) -> 302739.58 | D4: =INDEX(Table3[#All],MATCH(A4,Table13[#All],0)) -> #N/A

Sheet Segment vs Revenue
A1: Segment | B1: Revenue | C1: Revenue_Contribution
A2: Consumer | B2: =SUMIF(Table13[Segment],A2,Table13[Sales]) -> 586906.68 | C2: =B2/SUM(B2:B4) -> 0.35200129
A3: Corporate | B3: =SUMIF(Table13[Segment],A3,Table13[Sales]) -> 524863.58 | C3: =B3/SUM(B3:B5) -> 0.48578879
A4: Home Office | B4: =SUMIF(Table13[Segment],A4,Table13[Sales]) -> 555572.18 | C4: =B4/SUM(B4:B6) -> 1
